judoscale/__init__.py
judoscale/core/__init__.py
judoscale/core/adapter_api_client.py
judoscale/core/config.py
judoscale/core/metric.py
judoscale/core/metrics_store.py
judoscale/core/reporter.py
judoscale/django/__init__.py
judoscale/django/apps.py
judoscale/django/middleware.py
judoscale/flask/__init__.py
judoscale/flask/judoscale.py
judoscale_python-0.1.2.dist-info/LICENSE
judoscale_python-0.1.2.dist-info/WHEEL
judoscale_python-0.1.2.dist-info/METADATA
judoscale_python-0.1.2.dist-info/RECORD
